django_pdfkit/__init__.py
django_pdfkit/views.py
django_pdfkit/tests/__init__.py
django_pdfkit/tests/settings.py
django_pdfkit/tests/test_views.py
django_pdfkit/tests/urls.py
django_pdfkit/tests/templates/basic.html
django_pdfkit-0.3.1.dist-info/DESCRIPTION.rst
django_pdfkit-0.3.1.dist-info/METADATA
django_pdfkit-0.3.1.dist-info/RECORD
django_pdfkit-0.3.1.dist-info/WHEEL
django_pdfkit-0.3.1.dist-info/metadata.json
django_pdfkit-0.3.1.dist-info/top_level.txt
